AUTHORS.rst
CONTRIBUTING.rst
HISTORY.rst
LICENSE
MANIFEST.in
README.rst
setup.cfg
setup.py
docs/Makefile
docs/authors.rst
docs/conf.py
docs/contributing.rst
docs/femputadora.rst
docs/history.rst
docs/index.rst
docs/installation.rst
docs/make.bat
docs/modules.rst
docs/readme.rst
docs/usage.rst
docs/_build/html/_static/ajax-loader.gif
docs/_build/html/_static/comment-bright.png
docs/_build/html/_static/comment-close.png
docs/_build/html/_static/comment.png
docs/_build/html/_static/down-pressed.png
docs/_build/html/_static/down.png
docs/_build/html/_static/file.png
docs/_build/html/_static/minus.png
docs/_build/html/_static/plus.png
docs/_build/html/_static/up-pressed.png
docs/_build/html/_static/up.png
femputadora/__init__.py
femputadora/cli.py
femputadora/femputadora.py
femputadora.egg-info/PKG-INFO
femputadora.egg-info/SOURCES.txt
femputadora.egg-info/dependency_links.txt
femputadora.egg-info/entry_points.txt
femputadora.egg-info/not-zip-safe
femputadora.egg-info/requires.txt
femputadora.egg-info/top_level.txt
tests/__init__.py
tests/test_femputadora.py