Metadata-Version: 1.1
Name: femputadora
Version: 0.1
Summary: Femputadora-ChatBot
Home-page: https://github.com/juandavid8a/femputadora
Author: Juan David Ochoa
Author-email: juandavid8a@gmail.com
License: MIT license
Keywords: femputadora
Platform: UNKNOWN
Classifier: Development Status :: 2 - Pre-Alpha
Classifier: Intended Audience :: Developers
Classifier: License :: OSI Approved :: MIT License
Classifier: Natural Language :: English
Classifier: Programming Language :: Python :: 2
Classifier: Programming Language :: Python :: 2.7
Classifier: Programming Language :: Python :: 3
Classifier: Programming Language :: Python :: 3.4
Classifier: Programming Language :: Python :: 3.5
Classifier: Programming Language :: Python :: 3.6
